{
    "Total number of documents": 2847,
    "Total number of paragraphs": 1142359,
    "Average number of tokens per paragraph": 121.45944401015792,
    "Paragraph ID with max tokens": "20190215_10-K_1601712_mda_para737",
    "Max number of tokens": 10562,
    "Paragraph ID with min tokens": "20210224_10-K_46080_part1_item1_para27",
    "Min number of tokens": 2,
    "Length groups": {
        "100": 590163,
        "200": 347267,
        "300": 117522,
        "400": 36280,
        "500": 13069,
        "600": 5377,
        "700": 2816,
        "800": 1610,
        "900": 989,
        "1000": 602,
        "1100": 317,
        "1200": 274,
        "1300": 173,
        "1400": 136,
        "1500": 99,
        "1600": 70,
        "1700": 52,
        "1800": 33,
        "1900": 29,
        "2000": 19,
        "2100": 18,
        "2200": 33,
        "2300": 17,
        "2400": 19,
        "2500": 9,
        "2600": 7,
        "2700": 7,
        "2800": 7,
        "2900": 4,
        "3000": 7,
        "3100": 19,
        "3200": 13,
        "3300": 4,
        "3400": 4,
        "3500": 1,
        "3600": 3,
        "3700": 2,
        "3800": 0,
        "3900": 5,
        "4000": 1,
        "4100": 2,
        "4200": 1,
        "4300": 0,
        "4400": 0,
        "4500": 1,
        "4600": 0,
        "4700": 0,
        "4800": 0,
        "4900": 1,
        "5000": 1,
        "5100": 0,
        "5200": 0,
        "5300": 0,
        "5400": 2,
        "5500": 0,
        "5600": 0,
        "5700": 1,
        "5800": 0,
        "5900": 0,
        "6000": 0,
        "6100": 0,
        "6200": 0,
        "6300": 0,
        "6400": 0,
        "6500": 0,
        "6600": 0,
        "6700": 0,
        "6800": 0,
        "6900": 0,
        "7000": 0,
        "7100": 0,
        "7200": 0,
        "7300": 0,
        "7400": 0,
        "7500": 0,
        "7600": 0,
        "7700": 0,
        "7800": 0,
        "7900": 0,
        "8000": 0,
        "8100": 0,
        "8200": 0,
        "8300": 0,
        "8400": 0,
        "8500": 1,
        "8600": 1,
        "8700": 0,
        "8800": 0,
        "8900": 0,
        "9000": 0,
        "9100": 0,
        "9200": 0,
        "9300": 0,
        "9400": 0,
        "9500": 0,
        "9600": 1,
        "9700": 1,
        "9800": 1,
        "9900": 0,
        "10000": 0,
        "10100": 1,
        "10200": 0,
        "10300": 0,
        "10400": 0,
        "10500": 0,
        "10562": 1
    }
}